[
  {
    "checked_at": "2026-05-16",
    "source": "運動筆記",
    "url": "https://running.biji.co/",
    "source_type": "跑步新聞",
    "status": "穩定",
    "ok": true,
    "candidate_count": 5,
    "consecutive_failures": 0,
    "base_priority": 5,
    "effective_priority": 5,
    "error": ""
  },
  {
    "checked_at": "2026-05-16",
    "source": "動一動",
    "url": "https://www.don1don.com/",
    "source_type": "跑鞋新品 / 跑步專題",
    "status": "穩定",
    "ok": true,
    "candidate_count": 9,
    "consecutive_failures": 0,
    "base_priority": 5,
    "effective_priority": 5,
    "error": ""
  },
  {
    "checked_at": "2026-05-16",
    "source": "Bounce",
    "url": "https://bouncin.net/",
    "source_type": "跑鞋新品",
    "status": "穩定",
    "ok": true,
    "candidate_count": 2,
    "consecutive_failures": 0,
    "base_priority": 4,
    "effective_priority": 4,
    "error": ""
  },
  {
    "checked_at": "2026-05-16",
    "source": "Women's Health Taiwan",
    "url": "https://www.womenshealthmag.com/tw/fitness/",
    "source_type": "跑鞋選購 / 健康訓練",
    "status": "穩定",
    "ok": true,
    "candidate_count": 2,
    "consecutive_failures": 0,
    "base_priority": 3,
    "effective_priority": 3,
    "error": ""
  },
  {
    "checked_at": "2026-05-16",
    "source": "HK01 跑步",
    "url": "https://www.hk01.com/channel/跑步",
    "source_type": "跑步裝備 / 跑步知識",
    "status": "穩定",
    "ok": true,
    "candidate_count": 5,
    "consecutive_failures": 0,
    "base_priority": 3,
    "effective_priority": 3,
    "error": ""
  },
  {
    "checked_at": "2026-05-16",
    "source": "KENLU",
    "url": "https://kenlu.net/tag/running/",
    "source_type": "跑鞋評測 / 裝備情報",
    "status": "可用需觀察",
    "ok": true,
    "candidate_count": 0,
    "consecutive_failures": 0,
    "base_priority": 3,
    "effective_priority": 3,
    "error": ""
  },
  {
    "checked_at": "2026-05-16",
    "source": "KENLU 越野",
    "url": "https://kenlu.net/tag/trail-run/",
    "source_type": "越野跑鞋 / 越野訓練",
    "status": "可用需觀察",
    "ok": true,
    "candidate_count": 0,
    "consecutive_failures": 0,
    "base_priority": 3,
    "effective_priority": 3,
    "error": ""
  },
  {
    "checked_at": "2026-05-16",
    "source": "運動科學網",
    "url": "https://www.sportscience.com.tw/",
    "source_type": "訓練知識 / 運動科學",
    "status": "穩定",
    "ok": true,
    "candidate_count": 4,
    "consecutive_failures": 0,
    "base_priority": 3,
    "effective_priority": 3,
    "error": ""
  },
  {
    "checked_at": "2026-05-16",
    "source": "IR SPORTS",
    "url": "https://irsports.com.tw/",
    "source_type": "路跑活動 / 訓練資訊",
    "status": "穩定",
    "ok": true,
    "candidate_count": 1,
    "consecutive_failures": 0,
    "base_priority": 2,
    "effective_priority": 2,
    "error": ""
  },
  {
    "checked_at": "2026-05-16",
    "source": "udn 品牌",
    "url": "https://branda.udn.com/branda/index",
    "source_type": "品牌新品 / 運動消費",
    "status": "可用需觀察",
    "ok": true,
    "candidate_count": 0,
    "consecutive_failures": 0,
    "base_priority": 2,
    "effective_priority": 2,
    "error": ""
  }
]
